poetry_plugin_exec/__init__.py
poetry_plugin_exec/command.py
poetry_plugin_exec/plugins.py
poetry_plugin_exec-1.0.4.dist-info/LICENSE
poetry_plugin_exec-1.0.4.dist-info/METADATA
poetry_plugin_exec-1.0.4.dist-info/WHEEL
poetry_plugin_exec-1.0.4.dist-info/entry_points.txt
poetry_plugin_exec-1.0.4.dist-info/RECORD
