Metadata-Version: 2.3
Name: poetry-plugin-exec
Version: 1.0.4
Summary: Poetry plugin to configure and execute commands like npm run.
Author: Marcos Alonso
Author-email: contact@marcosalonso.dev
Requires-Python: >=3.9,<4.0
Classifier: Programming Language :: Python :: 3
Classifier: Programming Language :: Python :: 3.9
Classifier: Programming Language :: Python :: 3.10
Classifier: Programming Language :: Python :: 3.11
Classifier: Programming Language :: Python :: 3.12
Classifier: Programming Language :: Python :: 3.13
Requires-Dist: poetry (>=2.1.0,<3.0.0)
Requires-Dist: poetry-core (>=2.1.0,<3.0.0)
